Workbook

Sheet WBS Dictionary
A1: WBS ID | B1: Branch | C1: Work Package | D1: Hours | E1: Week | F1: Depends On | G1: Completion Criterion | H1: Plan Ref | I1: Critical Path | J1: Status | K1: % Complete
A2: 1.1.1 | B2: 1.0 | C2: Project charter | D2: 2 | E2: 0 | F2: - | G2: Scope, problem, success criteria approved | H2: - | I2: N | J2: Not started | K2: 0
A3: 1.1.2 | B3: 1.0 | C3: Technical design specification | D3: 2 | E3: 0 | F3: 1.1.1 | G3: Architecture, schemas, algorithms documented | H3: - | I3: N | J3: Not started | K3: 0
A4: 1.1.3 | B4: 1.0 | C4: WBS & schedule | D4: 1 | E4: 0 | F4: 1.1.2 | G4: All work decomposed; critical path identified | H4: - | I4: N | J4: Not started | K4: 0
A5: 1.2.1 | B5: 1.0 | C5: Risk register maintenance | D5: 2 | E5: 1-6 | F5: 1.1.3 | G5: Reviewed and dated every Monday | H5: - | I5: N | J5: Not started | K5: 0
A6: 1.2.2 | B6: 1.0 | C6: Cost guardrails & budget alarms | D6: 1 | E6: 1 | F6: 3.1.1 | G6: Alerts at $10/$25/$50 firing; egress alarm set | H6: T2 | I6: N | J6: Not started | K6: 0
A7: 1.2.3 | B7: 1.0 | C7: Weekly progress log | D7: 1 | E7: 1-6 | F7: - | G7: 6 dated entries: cost, volume, event rate | H7: - | I7: N | J7: Not started | K7: 0
A8: 1.3.1 | B8: 1.0 | C8: Data governance & ethics policy | D8: 1 | E8: 0 | F8: - | G8: Publishable without edits | H8: - | I8: N | J8: Not started | K8: 0
A9: 1.3.2 | B9: 1.0 | C9: robots.txt re-verification | D9: 0 | E9: 1-6 | F9: 1.3.1 | G9: Matrix re-checked weekly; changes logged | H9: - | I9: N | J9: Not started | K9: 0
A10: 2.1.1 | B10: 2.0 | C10: Repo skeleton & config loader | D10: 2 | E10: 1 | F10: - | G10: pytest tests/test_smoke.py green | H10: T1 | I10: N | J10: Not started | K10: 0
A11: 2.1.2 | B11: 2.0 | C11: Source definitions (4 portals) | D11: 1 | E11: 1 | F11: 2.1.1 | G11: 4 sources with sitemaps and URL patterns | H11: T1 | I11: N | J11: Not started | K11: 0
A12: 2.1.3 | B12: 2.0 | C12: Crawl frontier (SQLite, panel-aware) | D12: 4 | E12: 1 | F12: 2.1.1 | G12: 5 frontier tests green; 2-failure rule verified | H12: T4 | I12: Y | J12: Not started | K12: 0
A13: 2.1.4 | B13: 2.0 | C13: Sitemap poller with index recursion | D13: 2 | E13: 1 | F13: 2.1.3 | G13: Returns >=10k URLs for one live source | H13: T5 | I13: N | J13: Not started | K13: 0
... A65: 8.3.2 | B65: 8.0 | C65: Defence preparation & rehearsal | D65: 1 | E65: 6 | F65: 8.3.1 | G65: 4 questions answerable; rehearsed twice | H65: T24 | I65: N | J65: Not started | K65: 0
C66: TOTAL - WORK PACKAGES | D66: =SUM(D2:D65) -> 150

Sheet Roll-Up
A1: Effort Roll-Up by WBS Branch
A2: All values computed from the WBS Dictionary sheet - edit hours there, not here.
A4: WBS | B4: Element | C4: Hours | D4: % of Total | E4: Packages | F4: % Complete | G4: Earned Hours
A5: 1.0 | B5: Project Management & Governance | C5: =SUMIF('WBS Dictionary'!$B$2:$B$65,$A5,'WBS Dictionary'!$D$2:$D$65) -> 10 | D5: =IFERROR(C5/$C$14,0) -> 0.060606061 | E5: =COUNTIF('WBS Dictionary'!$B$2:$B$65,$A5) -> 8 | F5: =IFERROR(G5/C5,0) -> 0 | G5: =SUMPRODUCT(('WBS Dictionary'!$B$2:$B$65=$A5)*'WBS Dictionary'!$D$2:$D$65*'WBS Dictionary'!$K$2:$K$65) -> 0
A6: 2.0 | B6: Data Collection System | C6: =SUMIF('WBS Dictionary'!$B$2:$B$65,$A6,'WBS Dictionary'!$D$2:$D$65) -> 27 | D6: =IFERROR(C6/$C$14,0) -> 0.16363636 | E6: =COUNTIF('WBS Dictionary'!$B$2:$B$65,$A6) -> 12 | F6: =IFERROR(G6/C6,0) -> 0 | G6: =SUMPRODUCT(('WBS Dictionary'!$B$2:$B$65=$A6)*'WBS Dictionary'!$D$2:$D$65*'WBS Dictionary'!$K$2:$K$65) -> 0
A7: 3.0 | B7: Data Platform | C7: =SUMIF('WBS Dictionary'!$B$2:$B$65,$A7,'WBS Dictionary'!$D$2:$D$65) -> 12 | D7: =IFERROR(C7/$C$14,0) -> 0.072727273 | E7: =COUNTIF('WBS Dictionary'!$B$2:$B$65,$A7) -> 6 | F7: =IFERROR(G7/C7,0) -> 0 | G7: =SUMPRODUCT(('WBS Dictionary'!$B$2:$B$65=$A7)*'WBS Dictionary'!$D$2:$D$65*'WBS Dictionary'!$K$2:$K$65) -> 0
A8: 4.0 | B8: Data Processing & Quality | C8: =SUMIF('WBS Dictionary'!$B$2:$B$65,$A8,'WBS Dictionary'!$D$2:$D$65) -> 25 | D8: =IFERROR(C8/$C$14,0) -> 0.15151515 | E8: =COUNTIF('WBS Dictionary'!$B$2:$B$65,$A8) -> 8 | F8: =IFERROR(G8/C8,0) -> 0 | G8: =SUMPRODUCT(('WBS Dictionary'!$B$2:$B$65=$A8)*'WBS Dictionary'!$D$2:$D$65*'WBS Dictionary'!$K$2:$K$65) -> 0
A9: 5.0 | B9: Exploratory Data Analysis | C9: =SUMIF('WBS Dictionary'!$B$2:$B$65,$A9,'WBS Dictionary'!$D$2:$D$65) -> 15 | D9: =IFERROR(C9/$C$14,0) -> 0.090909091 | E9: =COUNTIF('WBS Dictionary'!$B$2:$B$65,$A9) -> 6 | F9: =IFERROR(G9/C9,0) -> 0 | G9: =SUMPRODUCT(('WBS Dictionary'!$B$2:$B$65=$A9)*'WBS Dictionary'!$D$2:$D$65*'WBS Dictionary'!$K$2:$K$65) -> 0
A10: 6.0 | B10: Predictive Models | C10: =SUMIF('WBS Dictionary'!$B$2:$B$65,$A10,'WBS Dictionary'!$D$2:$D$65) -> 25 | D10: =IFERROR(C10/$C$14,0) -> 0.15151515 | E10: =COUNTIF('WBS Dictionary'!$B$2:$B$65,$A10) -> 10 | F10: =IFERROR(G10/C10,0) -> 0 | G10: =SUMPRODUCT(('WBS Dictionary'!$B$2:$B$65=$A10)*'WBS Dictionary'!$D$2:$D$65*'WBS Dictionary'!$K$2:$K$65) -> 0
A11: 7.0 | B11: Results & Prescriptive Layer | C11: =SUMIF('WBS Dictionary'!$B$2:$B$65,$A11,'WBS Dictionary'!$D$2:$D$65) -> 11 | D11: =IFERROR(C11/$C$14,0) -> 0.066666667 | E11: =COUNTIF('WBS Dictionary'!$B$2:$B$65,$A11) -> 6 | F11: =IFERROR(G11/C11,0) -> 0 | G11: =SUMPRODUCT(('WBS Dictionary'!$B$2:$B$65=$A11)*'WBS Dictionary'!$D$2:$D$65*'WBS Dictionary'!$K$2:$K$65) -> 0
A12: 8.0 | B12: Deliverables & Defence | C12: =SUMIF('WBS Dictionary'!$B$2:$B$65,$A12,'WBS Dictionary'!$D$2:$D$65) -> 25 | D12: =IFERROR(C12/$C$14,0) -> 0.15151515 | E12: =COUNTIF('WBS Dictionary'!$B$2:$B$65,$A12) -> 8 | F12: =IFERROR(G12/C12,0) -> 0 | G12: =SUMPRODUCT(('WBS Dictionary'!$B$2:$B$65=$A12)*'WBS Dictionary'!$D$2:$D$65*'WBS Dictionary'!$K$2:$K$65) -> 0
A13: 9.0 | B13: Management Reserve (unallocated) | C13: 15 | D13: =IFERROR(C13/$C$14,0) -> 0.090909091 | E13: -
B14: TOTAL PROJECT EFFORT | C14: =SUM(C5:C13) -> 165 | D14: =IFERROR(C14/$C$14,0) -> 1 | E14: =SUM(E5:E12) -> 64 | F14: =IFERROR(G14/SUM(C5:C12),0) -> 0 | G14: =SUM(G5:G12) -> 0
A16: Management reserve is held against realised risk (see Risk Register), not scope growth.
A17: Earned Hours = sum of (package hours x % complete). Update % Complete in the WBS Dictionary.

Sheet Weekly Load
A1: Weekly Effort Load vs Capacity
A2: Capacity assumption (h/week) - editable: | D2: 27
A4: Week | B4: Dates | C4: Planned Hours | D4: Capacity | E4: Load % | F4: Status | G4: Key Milestone
A5: 0 | B5: Pre-project (planning) | C5: =SUMIF('WBS Dictionary'!$E$2:$E$65,$A5,'WBS Dictionary'!$D$2:$D$65) -> 6 | D5: 0 | E5: =IFERROR(C5/D5,0) -> 0 | F5: =IF(D5=0,"n/a",IF(E5>1.1,"OVER",IF(E5>1,"TIGHT","OK"))) -> n/a | G5: Charter, spec, WBS complete
A6: 1 | B6: Sep 14 - Sep 20 | C6: =SUMIF('WBS Dictionary'!$E$2:$E$65,$A6,'WBS Dictionary'!$D$2:$D$65) -> 34 | D6: =$D$2 -> 27 | E6: =IFERROR(C6/D6,0) -> 1.2592593 | F6: =IF(D6=0,"n/a",IF(E6>1.1,"OVER",IF(E6>1,"TIGHT","OK"))) -> OVER | G6: CRAWLER LIVE Sep 18; Report 1 Sep 20
A7: 2 | B7: Sep 21 - Sep 27 | C7: =SUMIF('WBS Dictionary'!$E$2:$E$65,$A7,'WBS Dictionary'!$D$2:$D$65) -> 30 | D7: =$D$2 -> 27 | E7: =IFERROR(C7/D7,0) -> 1.1111111 | F7: =IF(D7=0,"n/a",IF(E7>1.1,"OVER",IF(E7>1,"TIGHT","OK"))) -> OVER | G7: Spark cluster up; COHORT FROZEN Sep 25
A8: 3 | B8: Sep 28 - Oct 4 | C8: =SUMIF('WBS Dictionary'!$E$2:$E$65,$A8,'WBS Dictionary'!$D$2:$D$65) -> 26 | D8: =$D$2 -> 27 | E8: =IFERROR(C8/D8,0) -> 0.96296296 | F8: =IF(D8=0,"n/a",IF(E8>1.1,"OVER",IF(E8>1,"TIGHT","OK"))) -> OK | G8: Event-rate checkpoint; Report 2 Oct 4
A9: 4 | B9: Oct 5 - Oct 11 | C9: =SUMIF('WBS Dictionary'!$E$2:$E$65,$A9,'WBS Dictionary'!$D$2:$D$65) -> 17 | D9: =$D$2 -> 27 | E9: =IFERROR(C9/D9,0) -> 0.62962963 | F9: =IF(D9=0,"n/a",IF(E9>1.1,"OVER",IF(E9>1,"TIGHT","OK"))) -> OK | G9: Rent model meets MAPE target
A10: 5 | B10: Oct 12 - Oct 18 | C10: =SUMIF('WBS Dictionary'!$E$2:$E$65,$A10,'WBS Dictionary'!$D$2:$D$65) -> 25 | D10: =$D$2 -> 27 | E10: =IFERROR(C10/D10,0) -> 0.92592593 | F10: =IF(D10=0,"n/a",IF(E10>1.1,"OVER",IF(E10>1,"TIGHT","OK"))) -> OK | G10: PANEL CENSORED Oct 12; Report 3 Oct 18
A11: 6 | B11: Oct 19 - Oct 25 | C11: =SUMIF('WBS Dictionary'!$E$2:$E$65,$A11,'WBS Dictionary'!$D$2:$D$65) -> 9 | D11: =$D$2 -> 27 | E11: =IFERROR(C11/D11,0) -> 0.33333333 | F11: =IF(D11=0,"n/a",IF(E11>1.1,"OVER",IF(E11>1,"TIGHT","OK"))) -> OK | G11: Report 4 + oral defence Oct 25
B12: Continuous (weeks 1-6, ~0.5 h/wk) | C12: =SUMIF('WBS Dictionary'!$E$2:$E$65,"1-6",'WBS Dictionary'!$D$2:$D$65) -> 3 | G12: Risk review, progress log, robots.txt re-check
B13: Management reserve (unallocated) | C13: ='Roll-Up'!C13 -> 15
B14: TOTAL | C14: =SUM(C5:C13) -> 165
A16: Load % = Planned / Capacity. "OVER" above 110%, "TIGHT" above 100%.
A17: Week 1 is deliberately front-loaded: the crawler must be live by Sep 18 or survival labels are lost permanently.

Sheet Critical Path
A1: Critical Path - Zero-Float Work Packages
A2: A day lost on any package below moves the project end date.
A4: WBS ID | B4: Work Package | C4: Hours | D4: Week | E4: Depends On | F4: Why it is critical
A5: 2.1.3 | B5: Crawl frontier (SQLite, panel-aware) | C5: =INDEX('WBS Dictionary'!$D$2:$D$65,MATCH($A5,'WBS Dictionary'!$A$2:$A$65,0)) -> 4 | D5: 1 | E5: 2.1.1 | F5: Frontier is the prerequisite for any crawling at all.
A6: 2.2.2 | B6: Scrapy spider - batdongsan | C6: =INDEX('WBS Dictionary'!$D$2:$D$65,MATCH($A6,'WBS Dictionary'!$A$2:$A$65,0)) -> 6 | D6: 1 | E6: 2.1.3, 2.2.4 | F6: HARD DEADLINE Sep 18. Observation window cannot be back-filled.
A7: 2.2.4 | B7: S3 bronze batch writer | C7: =INDEX('WBS Dictionary'!$D$2:$D$65,MATCH($A7,'WBS Dictionary'!$A$2:$A$65,0)) -> 2 | D7: 1 | E7: 2.1.1 | F7: Without the writer, fetched pages are not persisted.
A8: 2.3.2 | B8: Full cohort freeze, stratified (Sep 25) | C8: =INDEX('WBS Dictionary'!$D$2:$D$65,MATCH($A8,'WBS Dictionary'!$A$2:$A$65,0)) -> 1 | D8: 2 | E8: 2.2.3 | F8: Cohort freeze date sets the start of every survival duration.
A9: 2.3.3 | B9: Daily liveness probe scheduler | C9: =INDEX('WBS Dictionary'!$D$2:$D$65,MATCH($A9,'WBS Dictionary'!$A$2:$A$65,0)) -> 2.5 | D9: 2 | E9: 2.3.2 | F9: 17 days of elapsed observation - cannot be compressed by effort.
A10: 2.4.1 | B10: EC2 deployment & cron scheduling | C10: =INDEX('WBS Dictionary'!$D$2:$D$65,MATCH($A10,'WBS Dictionary'!$A$2:$A$65,0)) -> 1 | D10: 1 | E10: 2.2.2 | F10: Unattended cron is what makes collection continuous.
A11: 4.1.3 | B11: Spark bronze->silver parse job | C11: =INDEX('WBS Dictionary'!$D$2:$D$65,MATCH($A11,'WBS Dictionary'!$A$2:$A$65,0)) -> 5 | D11: 2 | E11: 4.1.2, 3.2.3 | F11: Silver layer blocks dedup, panel, features and both models.
A12: 4.3.1 | B12: MinHash LSH dedup & canonicalisation | C12: =INDEX('WBS Dictionary'!$D$2:$D$65,MATCH($A12,'WBS Dictionary'!$A$2:$A$65,0)) -> 4 | D12: 2 | E12: 4.1.3 | F12: Unmerged re-posts corrupt survival labels irreversibly.
A13: 4.4.1 | B13: Panel fact table (listing x day) | C13: =INDEX('WBS Dictionary'!$D$2:$D$65,MATCH($A13,'WBS Dictionary'!$A$2:$A$65,0)) -> 1.5 | D13: 3 | E13: 4.3.1, 2.3.3 | F13: Panel assembly gates all survival work.
A14: 4.4.2 | B14: Right-censored survival labelling | C14: =INDEX('WBS Dictionary'!$D$2:$D$65,MATCH($A14,'WBS Dictionary'!$A$2:$A$65,0)) -> 1.5 | D14: 3 | E14: 4.4.1 | F14: Labels must exist before any model can be fitted.
A15: 6.1.2 | B15: Leakage-safe temporal split | C15: =INDEX('WBS Dictionary'!$D$2:$D$65,MATCH($A15,'WBS Dictionary'!$A$2:$A$65,0)) -> 2 | D15: 4 | E15: 6.1.1 | F15: Leakage guard - without it, all reported metrics are invalid.
A16: 6.2.4 | B16: price_gap scoring across all listings | C16: =INDEX('WBS Dictionary'!$D$2:$D$65,MATCH($A16,'WBS Dictionary'!$A$2:$A$65,0)) -> 1 | D16: 4 | E16: 6.2.3 | F16: price_gap is the feature linking Stage 1 to Stage 2.
... A20: 8.1.3 | B20: Report 3 - Model & Results (Oct 18) | C20: =INDEX('WBS Dictionary'!$D$2:$D$65,MATCH($A20,'WBS Dictionary'!$A$2:$A$65,0)) -> 6 | D20: 5 | E20: 6.x, 7.x | F20: Graded deliverable with a fixed external deadline.
B21: TOTAL CRITICAL-PATH EFFORT | C21: =SUM(C5:C20) -> 44.5
A23: Note: 2.3.3 consumes only 2.5 h of effort but 17 calendar days. Elapsed time, not effort, is the binding constraint.

Sheet Read Me
A1: WORK BREAKDOWN STRUCTURE
A2: Vietnam Urban Rental Market Intelligence
A4: Project | B4: End-to-end big data capstone: crawl Vietnamese rental portals, process on Spark, model fair rent and time-on-market, deliver four reports and an oral defence.
A6: Window | B6: 2026-09-14 to 2026-10-25 (6 weeks). Solo execution. 165 hours total effort.
A8: Owner | B8: Nguyen (nguyenpnt4@fpt.com)
A10: Source documents | B10: 01-project-charter.md - scope and success criteria 02-technical-design-spec.md - architecture and schemas 03-implementation-plan.md - task detail (Plan Ref column maps here) 04-schedule-and-milestones.md - dates and go/no-go checkpoints 05-risk-register.md - risks feeding the management reserve 07-work-breakdown-structure.md - narrative version of this workbook
A13: HOW TO USE
A15: Cells you edit | B15: Only the YELLOW cells. In 'WBS Dictionary' these are Status and % Complete (one row per work package). In 'Weekly Load' it is the capacity assumption in D2. Everything else is a formula and will recalculate on its own.
A17: Status values | B17: Not started / In progress / Blocked / Done. All rows ship as 'Not started' - that is the expected format, overwrite it as work proceeds.
A19: % Complete | B19: Enter as a percentage (0% to 100%). Roll-Up multiplies it by package hours to give Earned Hours, so partial progress is visible without any extra bookkeeping.
A21: Adding work | B21: Insert rows inside the existing data range so the SUMIF and SUMPRODUCT formulas expand with them. Adding a row below the TOTAL row will be excluded from every total.
A24: CONVENTIONS
A26: Blue text | B26: A hardcoded input, entered by hand rather than calculated.
A28: Yellow fill | B28: A cell you are expected to fill in or maintain.
A30: Red 'Y' | B30: Zero-float package - on the critical path. See the Critical Path sheet.
A32: Green fill | B32: A calculated total.
A35: ASSUMPTIONS
A37: Capacity 27 h/week | B37: Supplied by the project owner as realistic availability alongside other commitments. Editable in Weekly Load D2 - every load figure follows it.
A39: Reserve 15 h (9%) | B39: Held against realised risk (R-01 crawler delay, R-12 Oracle capacity, R-05 duplicate contamination, R-06 parser breakage), NOT against scope growth. 9% is thin for a project carrying two critical risks; this is acknowledged, and the pre-agreed cut list is the response when it runs out.
A41: Effort estimates | B41: Bottom-up, produced by the project owner and Claude during planning on 2026-09-11. No historical velocity data exists for this team of one, so these are judgement-based and should be re-baselined after Week 1 actuals.
A43: Week 0 work | B43: Charter, spec, governance policy and this WBS are already complete and are shown at zero capacity, so they do not inflate the six-week load.
A45: Exclusions | B45: Images/CNN features, Streamlit dashboard, Supabase serving layer, streaming ingestion, sale listings, social-media sources, Airflow, and transformer embeddings are OUT OF SCOPE. Starting any of them requires a documented change.
